{
  "economy_summary": "【🌍 地缘焦点】\n(1). 美伊局势出现急转弯，特朗普一方面宣称对伊军事行动结束，另一方面寻求五天内达成协议，中东能源通道霍尔木兹海峡的稳定性成为全球油价波动的核心变量。\n(2). 北朝正式将韩国定为“头号敌国”，朝鲜半岛地缘政治风险溢价上升，影响亚太市场避险情绪。\n\n【⚔️ 战争与冲突】\n(1). 伊朗外长称美方战争成本已达千亿美元，高昂的军事开支加剧了美国通胀压力与纳税人负担。\n(2). 俄乌冲突进入长期消耗阶段，俄军大规模使用无人机且日益依赖中国供应的关键物资，供应链安全成为大国博弈焦点。\n(3). 以色列拦截加沙救援船队引发欧洲多国（葡萄牙、西班牙）强烈抗议，中东局势的次生灾害正在割裂西方联盟。\n\n【🤝 外交动态】\n(1). 中美高层通话开启“习特会”铺路进程，但在经贸议题上的互表不满预示着新一轮关税博弈的到来。\n(2). 特朗普对盟友（德、英、西、意）展现强硬态度，威胁提高汽车关税并点名批评欧洲领导人，大西洋两岸贸易关系面临严峻考验。\n(3). 欧盟放宽并购规则以扶持本土巨头，旨在提升应对中美竞争的产业自主性，标志着保护主义在欧洲进一步抬头。\n\n【🐋 对未来一年的影响】\n(1). 能源危机恐将持续：中东冲突引发的天然气断供担忧可能导致2026年冬季能源价格再次飙升。\n(2). 全球供应链重构：美国对俄罗斯钯金征收重税及对华数字显示屏的关税限制，将迫使科技制造业加速寻找替代供应商，推高生产成本。",
  "items": [
    {
      "title": "特朗普致函国会通报美对伊军事行动结束",
      "sentiment": "Neutral",
      "impact": "中等",
      "summary": "特朗普通报军事行动阶段性结束并寻求五天内达成共识，若谈判成功将极大缓解国际油价压力，反之则面临能源供应断层。",
      "url": "#"
    },
    {
      "title": "中美高层通话为“习特会”铺路",
      "sentiment": "Neutral",
      "impact": "重大",
      "summary": "双方在经贸议题互表不满，市场担忧新一轮贸易摩擦，但沟通本身释放了避免冲突失控的信号。",
      "url": "https://www.zaochenbao.com/news/china/202605/0170747.html"
    },
    {
      "title": "特朗普威胁对欧盟汽车及卡车征收25%关税",
      "sentiment": "Negative",
      "impact": "重大",
      "summary": "此举将重创德国等欧洲传统工业大国，可能引发跨大西洋贸易战，导致全球汽车产业价值链受损。",
      "url": "#"
    },
    {
      "title": "美国商务部对俄罗斯钯征收132.83%关税",
      "sentiment": "Negative",
      "impact": "重大",
      "summary": "钯是半导体和汽车尾气净化器的关键材料，关税激增将直接推高高科技产品与汽车的制造成本。",
      "url": "#"
    },
    {
      "title": "北韩将韩国定为“头号敌国”并修改宪法",
      "sentiment": "Negative",
      "impact": "中等",
      "summary": "半岛局势急剧恶化，影响韩国主权信用评级预期，或导致外资在亚太地区的避险撤离。",
      "url": "#"
    },
    {
      "title": "霍尔木兹海峡受阻引发全球能源危机担忧",
      "sentiment": "Negative",
      "impact": "重大",
      "summary": "作为全球最重要的石油通道，该地区的任何军事威胁都会导致国际油价瞬间进入恐慌性上涨通道。",
      "url": "https://www.sbs.com.au/language/chinese/zh-hans/podcast-episode/looming-energy-crisis-has-widespread-and-severe-implications/w8k0ykq80"
    },
    {
      "title": "美联储宣布维持利率不变",
      "sentiment": "Neutral",
      "impact": "重大",
      "summary": "在通胀压力与战争开支并存的背景下，美联储维持高利率以稳定币值，但也压制了全球流动性扩张。",
      "url": "https://ckxxapp.ckxx.net/pages/2026/05/01/46af7808c14748a99283680d27b3d35b.html"
    },
    {
      "title": "DRAM价格一年内暴涨至8.8倍",
      "sentiment": "Negative",
      "impact": "重大",
      "summary": "受供应链波动及AI需求激增影响，存储芯片缺货将长期掣肘全球电子设备与AI服务器的交付进度。",
      "url": "#"
    },
    {
      "title": "欧盟放宽并购规则以抗衡中美企业",
      "sentiment": "Positive",
      "impact": "中等",
      "summary": "政策转向旨在打破反垄断僵局，通过内部整合打造具有国际竞争力的欧洲科技与工业巨头。",
      "url": "#"
    },
    {
      "title": "中国对非洲建交国家正式实施零关税",
      "sentiment": "Positive",
      "impact": "中等",
      "summary": "通过经贸让利强化在非影响力，有助于中国获取长期稳定的矿产资源供应并拓展新兴出口市场。",
      "url": "https://ckxxapp.ckxx.net/pages/2026/05/01/b72a5993c25d4c4d84b7f2e72992395b.html"
    },
    {
      "title": "中东冲突或致德国明年冬季天然气断供",
      "sentiment": "Negative",
      "impact": "重大",
      "summary": "地缘冲突外溢至能源物流，德国能源安全脆弱性再次暴露，或被迫重启高成本能源替代方案。",
      "url": "https://sputniknews.cn/20260502/1071062748.html"
    },
    {
      "title": "美国汽油均价创近四年来新高",
      "sentiment": "Negative",
      "impact": "重大",
      "summary": "能源通胀直接削弱美国家庭消费能力，可能倒逼白宫在对伊政策上采取更务实的缓和姿态。",
      "url": "#"
    },
    {
      "title": "TSMC市值超越沙特阿美重登全球第六",
      "sentiment": "Positive",
      "impact": "中等",
      "summary": "反映了市场对AI半导体算力的估值已超越传统石化能源，科技股成为全球市场的避风港。",
      "url": "#"
    },
    {
      "title": "俄罗斯日益依赖中国供应关键战争物资",
      "sentiment": "Neutral",
      "impact": "中等",
      "summary": "中俄经贸关系紧密化虽缓解了俄方压力，但也引发西方针对中国企业的次级制裁风险担忧。",
      "url": "#"
    },
    {
      "title": "西班牙首相桑切斯下月访华",
      "sentiment": "Positive",
      "impact": "中等",
      "summary": "在欧盟与中国贸易关系趋紧背景下，成员国寻求双边沟通，有助于缓和欧中关税对峙压力。",
      "url": "https://www.zaobao.com.sg/news/china/story20260324-8780942"
    },
    {
      "title": "五角大楼允许在保密网络中使用人工智能技术",
      "sentiment": "Positive",
      "impact": "中等",
      "summary": "AI军事化应用进入实操阶段，将催生巨大的军工科技采购需求，改变未来战争的经济成本模型。",
      "url": "#"
    },
    {
      "title": "中国多所高校加速成立理工类新专业",
      "sentiment": "Positive",
      "impact": "中等",
      "summary": "针对西方技术封锁，中国正通过教育改革强化人才储备，致力于长期解决“卡脖子”技术瓶颈。",
      "url": "https://www.zaochenbao.com/news/china/202605/0170733.html"
    },
    {
      "title": "巴西成为全球第三大外国直接投资目的地",
      "sentiment": "Positive",
      "impact": "中等",
      "summary": "随着地缘冲突导致资金撤出动荡地区，巴西等新兴市场国家正成为全球资本配置的新宠。",
      "url": "https://ckxxapp.ckxx.net/pages/2026/05/01/2ed9150a2ed1484b9c29c2ad84f1fba8.html"
    },
    {
      "title": "美国数字显示屏关税或减少对华依赖",
      "sentiment": "Negative",
      "impact": "中等",
      "summary": "美智库推动的脱钩政策将导致其本土电子产品组装成本大幅上涨，影响终端消费者福利。",
      "url": "#"
    },
    {
      "title": "大众汽车拟向中国车企开放欧洲闲置产能",
      "sentiment": "Neutral",
      "impact": "中等",
      "summary": "传统汽车巨头被迫转型，通过与中国车企合作来对冲产线停工风险，体现了中欧汽车产业链的深度交织。",
      "url": "https://www.zaochenbao.com/news/china/202605/0170732.html"
    }
  ],
  "date": "2026-05-02 07:45"
}