[
  {
    "id": "zaobao",
    "items": [
      {
        "title": "下午察：当美国圣诞褪去中国身影",
        "url": "https://www.zaochenbao.com/news/politics/202512/2460560.html"
      },
      {
        "title": "中国未满月婴孩治疗黄疸期间死亡 涉事人员停职",
        "url": "https://www.zaochenbao.com/news/china/202512/2460559.html"
      },
      {
        "title": "新法引发“哪位少爷吸了”争议 中国官方：法律面前一律平等",
        "url": "https://www.zaochenbao.com/news/china/202512/2460558.html"
      },
      {
        "title": "港媒：料解放军驻港部队司令员彭京堂任武警副司令",
        "url": "https://www.zaochenbao.com/news/hkMacao/202512/2460557.html"
      },
      {
        "title": "中国足协纪律委员会原主任王小平受贿案二审维持原判",
        "url": "https://www.zaochenbao.com/news/china/202512/2460556.html"
      },
      {
        "title": "美最高法院初步裁定政府不能向芝加哥派遣军队",
        "url": "https://www.zaochenbao.com/news/politics/202512/2460555.html"
      },
      {
        "title": "委内瑞拉议会一致通过新法 应对美国海上拦截封锁",
        "url": "https://www.zaochenbao.com/news/politics/202512/2460554.html"
      },
      {
        "title": "日本京都府一农场确认高致病性禽流感疫情",
        "url": "https://www.zaochenbao.com/news/politics/202512/2460553.html"
      },
      {
        "title": "教宗良十四世呼吁全球在圣诞节休战24小时",
        "url": "https://www.zaochenbao.com/news/politics/202512/2460552.html"
      },
      {
        "title": "澳洲新南威尔士通过反恐法案 收紧枪支管控",
        "url": "https://www.zaochenbao.com/news/politics/202512/2460551.html"
      },
      {
        "title": "韩国法院对两名前高官签发追加逮捕令",
        "url": "https://www.zaochenbao.com/news/politics/202512/2460550.html"
      },
      {
        "title": "粤车车主不熟悉香港交通 港议员吁市民礼让",
        "url": "https://www.zaochenbao.com/news/hkMacao/202512/2460549.html"
      },
      {
        "title": "冯忠华任广州市委书记 郭永航另有任用",
        "url": "https://www.zaochenbao.com/news/Chronicles/202512/2460548.html"
      },
      {
        "title": "威胁对卢秀燕脑门开枪 台中女警被收押",
        "url": "https://www.zaochenbao.com/news/taiwan/202512/2460547.html"
      },
      {
        "title": "中国批评美国威胁拉美和加勒比地区和平与安全",
        "url": "https://www.zaochenbao.com/news/politics/202512/2460546.html"
      },
      {
        "title": "国台办敦促台民众认清赖政府台独路线极端危险性",
        "url": "https://www.zaochenbao.com/news/taiwan/202512/2460545.html"
      },
      {
        "title": "标普将万科评级下调至选择性违约",
        "url": "https://www.zaochenbao.com/news/china/202512/2460544.html"
      },
      {
        "title": "港媒：解放军空军司令政委缺席晋衔仪式",
        "url": "https://www.zaochenbao.com/news/hkMacao/202512/2460543.html"
      },
      {
        "title": "中国大陆公安悬赏追捕两名台湾居民",
        "url": "https://www.zaochenbao.com/news/taiwan/202512/2460542.html"
      },
      {
        "title": "评论：美国2025年第三季度经济增长4.3%",
        "url": "https://www.zaochenbao.com/news/opinion/202512/2460541.html"
      },
      {
        "title": "评论：美国2025年第三季度经济增长4.3%",
        "url": "https://www.zaochenbao.com/news/opinion/202512/2460540.html"
      },
      {
        "title": "吴丰山请辞海基会董事长主因 据报是谢长廷掌台日关系协会",
        "url": "https://www.zaochenbao.com/news/taiwan/202512/2460539.html"
      },
      {
        "title": "骑车进小区送餐受限 长沙外卖员聚集抗议",
        "url": "https://www.zaochenbao.com/news/china/202512/2460538.html"
      },
      {
        "title": "五角大楼报告称中国军事扩张使美国本土更趋脆弱",
        "url": "https://www.zaochenbao.com/news/politics/202512/2460537.html"
      },
      {
        "title": "莫斯科南部发生爆炸两人伤 靠近俄将领遇害地点",
        "url": "https://www.zaochenbao.com/news/politics/202512/2460536.html"
      },
      {
        "title": "法国要求欧盟采取行动 应对中国对乳制品加征关税",
        "url": "https://www.zaochenbao.com/news/china/202512/2460531.html"
      },
      {
        "title": "京东法国仓储遭盗 公司称警方介入调查",
        "url": "https://www.zaochenbao.com/news/china/202512/2460530.html"
      },
      {
        "title": "中国商飞C919交付进度不及预期 或仅完成一半目标",
        "url": "https://www.zaochenbao.com/news/china/202512/2460529.html"
      },
      {
        "title": "江西彭泽县发生车辆落水事故致八死",
        "url": "https://www.zaochenbao.com/news/china/202512/2460528.html"
      },
      {
        "title": "中国严格直播电商食品安全监管",
        "url": "https://www.zaochenbao.com/news/china/202512/2460527.html"
      }
    ]
  },
  {
    "id": "sputniknewscn",
    "items": [
      {
        "title": "俄联邦安全会议副主席：乌克兰冲突根源是西方的侵略性政策",
        "url": "https://sputniknews.cn/20251224/1069055472.html"
      },
      {
        "title": "俄工贸部：搭载俄VK-800发动机的“贝加尔”飞机完成首飞",
        "url": "https://sputniknews.cn/20251224/1069055258.html"
      },
      {
        "title": "俄罗斯计划在2036年前建成月球发电站",
        "url": "https://sputniknews.cn/20251224/1069055353.html"
      },
      {
        "title": "专家：中韩政治互信加强，具有广阔合作前景",
        "url": "https://sputniknews.cn/20251224/1069054921.html"
      },
      {
        "title": "普京向阿塞拜疆总统致以生日祝福",
        "url": "https://sputniknews.cn/20251224/1069054811.html"
      },
      {
        "title": "莫斯科南部爆炸致两名交通警察及其附近的可疑人员身亡",
        "url": "https://sputniknews.cn/20251224/1069054703.html"
      },
      {
        "title": "中国专家代表团高度评价莫斯科动物园大熊猫饲养条件",
        "url": "https://sputniknews.cn/20251224/1069054490.html"
      },
      {
        "title": "中国国台办回应日本盯上在台湾的大熊猫：痴人说梦",
        "url": "https://sputniknews.cn/20251224/1069054383.html"
      },
      {
        "title": "中国常驻联合国副代表：美方一系列言行导致加勒比地区局势持续紧张",
        "url": "https://sputniknews.cn/20251224/1069054258.html"
      },
      {
        "title": "委常驻联合国代表：真正的威胁并非委内瑞拉，而是美国现政府",
        "url": "https://sputniknews.cn/20251224/1069054075.html"
      },
      {
        "title": "俄国防部：防空部队一夜间击落172架乌克兰无人机",
        "url": "https://sputniknews.cn/20251224/1069053867.html"
      },
      {
        "title": "中国国台办：要求美方立即停止武装台湾，停止纵容支持“台独”分裂势力",
        "url": "https://sputniknews.cn/20251224/1069053763.html"
      },
      {
        "title": "俄军夺取安德烈耶夫卡居民点近半区域，乌军士兵开始溃逃",
        "url": "https://sputniknews.cn/20251224/1069053394.html"
      },
      {
        "title": "欧盟前“外长”案中牵扯的欧盟外交官培训项目围绕乌克兰设置课程",
        "url": "https://sputniknews.cn/20251224/1069053635.html"
      },
      {
        "title": "媒体：美国试图扣押第三艘与委内瑞拉相关的“贝拉1号”油轮",
        "url": "https://sputniknews.cn/20251224/1069053299.html"
      },
      {
        "title": "乌军抱怨在扎波罗热州无法躲避俄军的打击",
        "url": "https://sputniknews.cn/20251224/1069053097.html"
      },
      {
        "title": "莫斯科华铭中文学测中心将首次举办新版HSK考试",
        "url": "https://sputniknews.cn/20251224/1069052983.html"
      },
      {
        "title": "五角大楼：中国军队日益精进且更具韧性",
        "url": "https://sputniknews.cn/20251224/1069052863.html"
      },
      {
        "title": "2025年俄钻石开采公司阿尔罗萨开采量预计将达2970万克拉",
        "url": "https://sputniknews.cn/20251224/1069052723.html"
      },
      {
        "title": "泰柬两军将于周三开启停火谈判",
        "url": "https://sputniknews.cn/20251224/1069052613.html"
      }
    ]
  },
  {
    "id": "cankaoxiaoxi",
    "items": [
      {
        "title": "外媒：比利时加入指控以色列种族灭绝诉讼案",
        "url": "https://ckxxapp.ckxx.net/pages/2025/12/24/bdcb0fdbff7f4b5b86a3e4e8a56698f2.html"
      },
      {
        "title": "俄媒：俄罗斯强烈谴责美国在委内瑞拉海岸扣押油轮",
        "url": "https://ckxxapp.ckxx.net/pages/2025/12/24/f17f51fe64d44f7ab1ce23cab37e6e11.html"
      },
      {
        "title": "外媒：利比亚军队总参谋长在空难中身亡",
        "url": "https://ckxxapp.ckxx.net/pages/2025/12/24/a6963e87de1c4e23af685334b8e1e023.html"
      },
      {
        "title": "停电致美国标准时间变慢4.8微秒",
        "url": "https://ckxxapp.ckxx.net/pages/2025/12/24/d687e80d9ef145c08879840189f734e3.html"
      },
      {
        "title": "法国将迎十余年来最冷圣诞节",
        "url": "https://ckxxapp.ckxx.net/pages/2025/12/24/557730fdd70e4538a67b21390f8070fb.html"
      },
      {
        "title": "日本政客盯上大陆赠台大熊猫，国台办发出警告",
        "url": "https://ckxxapp.ckxx.net/pages/2025/12/24/8c837c2114ac49f2abf230338a34a757.html"
      },
      {
        "title": "国台办回应超八百万人参与联署“弹劾赖清德”活动",
        "url": "https://ckxxapp.ckxx.net/pages/2025/12/24/bb8f4215fe0147c08b98d135c8ec38eb.html"
      },
      {
        "title": "国台办“把脉”“台湾病”",
        "url": "https://ckxxapp.ckxx.net/pages/2025/12/24/d7b364657b3e4804a0d30adf8b7046dc.html"
      },
      {
        "title": "国台办回应谷辣斯：宵小之徒 可耻可悲可怜",
        "url": "https://ckxxapp.ckxx.net/pages/2025/12/24/01d078efe6b24100a1a99638c1fd3c71.html"
      },
      {
        "title": "国台办批台当局挥霍台湾老百姓的血汗钱换取所谓“外交空间”",
        "url": "https://ckxxapp.ckxx.net/pages/2025/12/24/adfc195afdca476aa00f9823f109baf0.html"
      },
      {
        "title": "国台办要求美方不得实施法案涉台条款并消除负面影响",
        "url": "https://ckxxapp.ckxx.net/pages/2025/12/24/9066618ec5954e4bb2554be8f0c6d0ee.html"
      },
      {
        "title": "台要建“民主防御机制” 国台办回应：“台独”分裂势力难逃国家法律制裁",
        "url": "https://ckxxapp.ckxx.net/pages/2025/12/24/cbb026eb169d4f82a49654e19c4a44b3.html"
      },
      {
        "title": "以色列敌对行动令巴民众恐惧不断",
        "url": "https://ckxxapp.ckxx.net/pages/2025/12/24/9bbab1b89bfb4e86b02730aa515443f9.html"
      },
      {
        "title": "国台办就公安机关依法征集2名台湾居民违法犯罪线索答记者问",
        "url": "https://ckxxapp.ckxx.net/pages/2025/12/24/0233069e302c497a91343cccab42c056.html"
      },
      {
        "title": "专家：儿童死亡人数上升与西方削减援助有关",
        "url": "https://ckxxapp.ckxx.net/pages/2025/12/24/34f435b3a504498d9850e7ce71f2a8dd.html"
      },
      {
        "title": "韩媒：日本强征韩籍军人遗属首次在韩起诉靖国神社要求取消合祀",
        "url": "https://ckxxapp.ckxx.net/pages/2025/12/24/a0850c98315d4a18b13796e700fcd34a.html"
      },
      {
        "title": "新加坡前外长：美国不会越过台湾问题“红线”",
        "url": "https://ckxxapp.ckxx.net/pages/2025/12/24/15954d9c7e764a2c8882d2807b9c87b6.html"
      },
      {
        "title": "台机构警告岛内产业分化严重",
        "url": "https://ckxxapp.ckxx.net/pages/2025/12/24/069aa146b5524286a276feece42531b0.html"
      },
      {
        "title": "中国研发新一代低成本货运飞船",
        "url": "https://ckxxapp.ckxx.net/pages/2025/12/24/760eb33843ea4533a92dacc2893b1c38.html"
      },
      {
        "title": "大学生团队格斗机器人赢得国际比赛 港媒：中国机器人“系统集成”实力增强",
        "url": "https://ckxxapp.ckxx.net/pages/2025/12/24/72c805afabd1461b906c1c9eaecd74c4.html"
      },
      {
        "title": "英媒：中国引领清洁燃料商业化进程",
        "url": "https://ckxxapp.ckxx.net/pages/2025/12/24/313b6e3be806435b9a4f1b50d19e654b.html"
      },
      {
        "title": "非媒：中国科技发展打破西方固有偏见",
        "url": "https://ckxxapp.ckxx.net/pages/2025/12/24/1ad4f577bd0e45f0bc2c40dd006dd2d5.html"
      },
      {
        "title": "日媒：侵华日军遗留化武贻害无穷",
        "url": "https://ckxxapp.ckxx.net/pages/2025/12/24/5130180414a84ec88bbf72b6d58d661a.html"
      },
      {
        "title": "毕马威调查显示：跨国企业坚定投资中国",
        "url": "https://ckxxapp.ckxx.net/pages/2025/12/24/aab9b4632ceb4c009efd5f89dfa37b28.html"
      },
      {
        "title": "外媒：四大全球倡议推动建设更美好世界",
        "url": "https://ckxxapp.ckxx.net/pages/2025/12/24/0cfb70af30914a60b0b0ba088a2e58e2.html"
      },
      {
        "title": "法里德·扎卡里亚文章 新国安战略“让美国再次狭隘”",
        "url": "https://ckxxapp.ckxx.net/pages/2025/12/23/32adf4b8821f45909b46947de7e03d5f.html"
      },
      {
        "title": "特朗普：爱泼斯坦案转移了对共和党成就的关注",
        "url": "https://ckxxapp.ckxx.net/pages/2025/12/23/e05234804fb846f496dfb2b90dcdc9f9.html"
      },
      {
        "title": "特朗普称美国“必须得到格陵兰岛”",
        "url": "https://ckxxapp.ckxx.net/pages/2025/12/23/7d626fef38de4c64bf7dd64b339210f6.html"
      },
      {
        "title": "特朗普：马杜罗主动下台将是“明智之举”",
        "url": "https://ckxxapp.ckxx.net/pages/2025/12/23/16d345e270184e41b5380ac49f1b3184.html"
      },
      {
        "title": "马杜罗回击特朗普：最好把精力放在国内问题上",
        "url": "https://ckxxapp.ckxx.net/pages/2025/12/23/36d77ed57bd44452b8a06c682550249c.html"
      }
    ]
  },
  {
    "id": "kaopu",
    "items": [
      {
        "title": "中国黄金巨头金雅福70亿人民币理财爆雷",
        "url": "https://www.zaobao.com.sg/realtime/china/story20251224-8010970"
      },
      {
        "title": "辽宁给农民评职称  最高为正高级",
        "url": "https://www.zaobao.com.sg/realtime/china/story20251224-8010858"
      },
      {
        "title": "AIT副处长与国民党副主席会面强调支持台湾强化防卫能力",
        "url": "https://www.zaobao.com.sg/realtime/china/story20251224-8010854"
      },
      {
        "title": "移民争议导致美籍教宗与美国政府走向决裂？",
        "url": "https://www.bbc.com/zhongwen/articles/cjwy5vzz4ggo/simp"
      },
      {
        "title": "中国网民转发高速路事故视频 疑有交警要求删除爆粗口",
        "url": "https://www.zaobao.com.sg/realtime/china/story20251224-8010647"
      },
      {
        "title": "骗81岁老雇主密码 女佣盗提万元存款",
        "url": "https://www.zaobao.com.sg/realtime/singapore/story20251224-8010712"
      },
      {
        "title": "与柬埔寨对话前 泰国军方列明要求",
        "url": "https://www.zaobao.com.sg/realtime/world/story20251224-8010554"
      },
      {
        "title": "美国人节日购物季负债增 逾三成消费者平均欠1569新元",
        "url": "https://www.zaobao.com.sg/realtime/world/story20251224-8010627"
      },
      {
        "title": "统一教的“政治运作法”……为邀请VIP全面动用青瓦台与国会人脉",
        "url": "http://china.hani.co.kr/arti/politics/16315.html"
      },
      {
        "title": "Grab明年调高平台与合作伙伴费 每趟上调3角",
        "url": "https://www.zaobao.com.sg/realtime/singapore/story20251224-8010319"
      },
      {
        "title": "借教武术性侵少女 六旬乩童罪成",
        "url": "https://www.zaobao.com.sg/realtime/singapore/story20251224-8010655"
      },
      {
        "title": "日本2026年度预算预计连续两年创新高",
        "url": "http://cn.nikkei.com/politicsaeconomy/politicsasociety/60835-2025-12-24-15-06-21.html"
      },
      {
        "title": "台湾25年来首次在圣诞节放假",
        "url": "https://www.zaobao.com.sg/realtime/china/story20251224-8010619"
      },
      {
        "title": "中纪委：着力破解新型腐败和隐性腐败调查难题",
        "url": "https://www.zaobao.com.sg/realtime/china/story20251224-8010616"
      },
      {
        "title": "下午察：美国圣诞褪去中国身影",
        "url": "https://www.zaobao.com.sg/realtime/china/story20251224-8007171"
      },
      {
        "title": "兀兰食阁命案死者为退休空服员 女儿：父富正义感",
        "url": "https://www.zaobao.com.sg/realtime/singapore/story20251224-8010539"
      },
      {
        "title": "美国贝莱德或撤回巴拿马港口运营权收购计划",
        "url": "http://cn.nikkei.com/politicsaeconomy/investtrade/60834-2025-12-24-14-42-05.html"
      },
      {
        "title": "揭秘特朗普时代的总统赦免新“快速通道”",
        "url": "https://cn.wsj.com/articles/trump-presidential-pardon-process-610a95ab"
      },
      {
        "title": "法国议会通过“特别法”草案 保障国家机构正常运转",
        "url": "https://www.zaobao.com.sg/realtime/world/story20251224-8009953"
      },
      {
        "title": "欧美货币政策趋势生变，成为日元贬值原因之一",
        "url": "http://cn.nikkei.com/politicsaeconomy/stockforex/60833-2025-12-24-14-24-54.html"
      },
      {
        "title": "俄罗斯对乌克兰战争的今日发展：乌克兰扎波罗热遭受致命袭击",
        "url": "https://chinese.aljazeera.net/news/liveblog/2025/12/24/%e4%bf%84%e7%bd%97%e6%96%af%e5%af%b9%e4%b9%8c%e5%85%8b%e5%85%b0%e6%88%98%e4%ba%89%e7%9a%84%e4%bb%8a%e6%97%a5%e5%8f%91%e5%b1%95%e4%b9%8c%e5%85%8b%e5%85%b0%e6%89%8e%e6%b3%a2%e7%bd%97%e7%83%ad"
      },
      {
        "title": "乌克兰在停电危机中迎来又一个圣诞节",
        "url": "https://cn.wsj.com/articles/%E4%B9%8C%E5%85%8B%E5%85%B0%E5%9C%A8%E5%81%9C%E7%94%B5%E5%8D%B1%E6%9C%BA%E4%B8%AD%E8%BF%8E%E6%9D%A5%E5%8F%88%E4%B8%80%E4%B8%AA%E5%9C%A3%E8%AF%9E%E8%8A%82-d32e97d2"
      },
      {
        "title": "中国未满月婴孩治疗黄疸期间死亡 涉事人员停职",
        "url": "https://www.zaobao.com.sg/realtime/china/story20251224-8010209"
      },
      {
        "title": "文在寅呼吁：应尽快发表终战宣言、签订和平协定，正式结束战争状态",
        "url": "http://china.hani.co.kr/arti/politics/16314.html"
      },
      {
        "title": "新法引发“哪位少爷吸了”争议 中国官方：法律面前一律平等",
        "url": "https://www.zaobao.com.sg/realtime/china/story20251224-8010162"
      },
      {
        "title": "这位营销大师正试图让我们重新爱上迪士尼",
        "url": "https://cn.wsj.com/articles/%E8%BF%99%E4%BD%8D%E8%90%A5%E9%94%80%E5%A4%A7%E5%B8%88%E6%AD%A3%E8%AF%95%E5%9B%BE%E8%AE%A9%E6%88%91%E4%BB%AC%E9%87%8D%E6%96%B0%E7%88%B1%E4%B8%8A%E8%BF%AA%E5%A3%AB%E5%B0%BC-64840b50"
      },
      {
        "title": "媒體：中國網軍在菲律賓發動輿論戰",
        "url": "https://www.dw.com/zh/媒體：中國網軍在菲律賓發動輿論戰/a-75291227"
      },
      {
        "title": "美最高法院初步裁定政府不能向芝加哥派遣军队",
        "url": "https://www.zaobao.com.sg/realtime/world/story20251224-8009066"
      },
      {
        "title": "港媒：料解放军驻港部队司令员彭京堂任武警副司令",
        "url": "https://www.zaobao.com.sg/realtime/china/story20251224-8009164"
      },
      {
        "title": "委内瑞拉议会一致通过新法 应对美国海上拦截封锁",
        "url": "https://www.zaobao.com.sg/realtime/world/story20251224-8009573"
      }
    ]
  }
]