[
  {
    "id": "zaobao",
    "items": [
      {
        "title": "体育总局：冬奥会中国代表团运动成绩和精神文明双丰收",
        "url": "https://www.zaochenbao.com/news/china/202603/0165715.html"
      },
      {
        "title": "伊朗革命卫队：我们失去了伟大领袖",
        "url": "https://www.zaochenbao.com/news/politics/202603/0165714.html"
      },
      {
        "title": "中国约三分之一原油供应来自经由霍尔木兹海峡运输的油轮",
        "url": "https://www.zaochenbao.com/news/china/202603/0165713.html"
      },
      {
        "title": "中东局势紧张 香港多班航班取消或延期",
        "url": "https://www.zaochenbao.com/news/hkMacao/202603/0165712.html"
      },
      {
        "title": "伊朗宣布自今起开始为期40天国家哀悼",
        "url": "https://www.zaochenbao.com/news/politics/202603/0165711.html"
      },
      {
        "title": "伊朗媒体证实哈梅内伊已死亡",
        "url": "https://www.zaochenbao.com/news/politics/202603/0165710.html"
      },
      {
        "title": "伊朗官员否认哈梅内伊身亡 但伊朗媒体证实死讯",
        "url": "https://www.zaochenbao.com/news/politics/202603/0165709.html"
      },
      {
        "title": "中国央视：哈梅内伊遇袭身亡",
        "url": "https://www.zaochenbao.com/news/politics/202603/0165708.html"
      },
      {
        "title": "消息：美以瞄准哈梅内伊召开会议发动袭击",
        "url": "https://www.zaochenbao.com/news/politics/202603/0165707.html"
      },
      {
        "title": "伊朗媒体：最高领袖哈梅内伊的四名亲属遇难",
        "url": "https://www.zaochenbao.com/news/politics/202603/0165706.html"
      },
      {
        "title": "中国驻以色列使馆吁在以中国公民转移至以安全地区避险",
        "url": "https://www.zaochenbao.com/news/china/202603/0165705.html"
      },
      {
        "title": "五粮液董事长曾从钦被查",
        "url": "https://www.zaochenbao.com/news/Chronicles/202603/0165704.html"
      },
      {
        "title": "美以袭击伊朗 赖清德：与全球伙伴保持密切联系与沟通",
        "url": "https://www.zaochenbao.com/news/china/202603/0165703.html"
      },
      {
        "title": "傅聪：中国强调伊朗及其他地区国家主权必须得到尊重",
        "url": "https://www.zaochenbao.com/news/china/202603/0165702.html"
      },
      {
        "title": "杭州两只大熊猫接连死亡",
        "url": "https://www.zaochenbao.com/news/china/202603/0165701.html"
      },
      {
        "title": "刘嘉铿：领取公积金 65岁或70岁？",
        "url": "https://www.zaochenbao.com/news/opinion/202603/0165700.html"
      },
      {
        "title": "任其：春日谈吃",
        "url": "https://www.zaochenbao.com/news/opinion/202603/0165699.html"
      },
      {
        "title": "吴汉钧：法槌挡不了特朗普",
        "url": "https://www.zaochenbao.com/news/opinion/202603/0165698.html"
      },
      {
        "title": "叶鹏飞：特朗普关税遭否决的法治意义",
        "url": "https://www.zaochenbao.com/news/opinion/202603/0165697.html"
      },
      {
        "title": "严孟达：从功夫熊猫到功夫机器人",
        "url": "https://www.zaochenbao.com/news/opinion/202603/0165696.html"
      },
      {
        "title": "王慧容：生育率从哪里重启？",
        "url": "https://www.zaochenbao.com/news/opinion/202603/0165695.html"
      },
      {
        "title": "中国特稿：赛博朋克+烟火气 短视频放大山城奇景 中外网红炒热魔幻重庆",
        "url": "https://www.zaochenbao.com/news/china/202603/0165694.html"
      },
      {
        "title": "特朗普：伊朗最高领袖哈梅内伊在袭击中身亡",
        "url": "https://www.zaochenbao.com/news/politics/202603/0165693.html"
      },
      {
        "title": "伊朗外长：最高领袖哈梅内伊安好 即将发表讲话",
        "url": "https://www.zaochenbao.com/news/politics/202603/0165692.html"
      },
      {
        "title": "美以袭击伊朗引发反击 中东烽烟四起紧张瞬间升级",
        "url": "https://www.zaochenbao.com/news/politics/202603/0165691.html"
      },
      {
        "title": "华润集团副总经理韩嵩被查 系主动投案",
        "url": "https://www.zaochenbao.com/news/china/202603/0165690.html"
      },
      {
        "title": "中国推“健康第一”教育理念 清华重申学生不会游泳不能毕业",
        "url": "https://www.zaochenbao.com/news/china/202602/2865682.html"
      },
      {
        "title": "美官员：避免激怒习近平 特朗普4月访华前搁置对台军售",
        "url": "https://www.zaochenbao.com/news/taiwan/202602/2865677.html"
      },
      {
        "title": "美媒称特朗普会推迟对台军售 台专家忧“台湾之盾”延宕",
        "url": "https://www.zaochenbao.com/news/taiwan/202602/2865676.html"
      },
      {
        "title": "中国外交部：伊朗国家主权应得到尊重",
        "url": "https://www.zaochenbao.com/news/china/202602/2865675.html"
      }
    ]
  },
  {
    "id": "sputniknewscn",
    "items": [
      {
        "title": "美媒：美国认为在对伊朗的行动中约有40名伊朗官员丧生",
        "url": "https://sputniknews.cn/20260301/1069989875.html"
      },
      {
        "title": "韩媒：韩国总统向朝鲜提议摒弃敌对，和平共处",
        "url": "https://sputniknews.cn/20260301/1069989272.html"
      },
      {
        "title": "伊朗总统办公室：必将对最高领袖之死进行报复，要求满足前决不收手",
        "url": "https://sputniknews.cn/20260301/1069989749.html"
      },
      {
        "title": "伊朗伊斯兰革命卫队宣布启动“伊朗武装部队史上最猛烈的进攻行动”",
        "url": "https://sputniknews.cn/20260301/1069989156.html"
      },
      {
        "title": "特朗普称已有在哈梅内伊死后领导伊朗的候选人",
        "url": "https://sputniknews.cn/20260301/1069989054.html"
      },
      {
        "title": "美军方公布对伊朗打击行动视频",
        "url": "https://sputniknews.cn/20260301/1069988921.html"
      },
      {
        "title": "以总理：对伊朗之战“需多久就打多久”",
        "url": "https://sputniknews.cn/20260301/1069988711.html"
      },
      {
        "title": "媒体：伊朗政府宣布最高领袖逝世后举行为期40天的哀悼",
        "url": "https://sputniknews.cn/20260301/1069988812.html"
      },
      {
        "title": "中方对美以对伊朗发动军事打击深表关切",
        "url": "https://sputniknews.cn/20260301/1069988561.html"
      },
      {
        "title": "伊朗最高领袖阿里·哈梅内伊身亡",
        "url": "https://sputniknews.cn/20260301/1069988377.html"
      },
      {
        "title": "韩媒：朝鲜大规模更换与韩边境前沿部队指挥官",
        "url": "https://sputniknews.cn/20260301/1069988270.html"
      },
      {
        "title": "伊朗常驻联合国代表：针对伊朗的袭击已致数百人伤亡",
        "url": "https://sputniknews.cn/20260301/1069988126.html"
      },
      {
        "title": "消息人士：伊朗与美以冲突进入海战阶段",
        "url": "https://sputniknews.cn/20260301/1069987968.html"
      },
      {
        "title": "以色列军方通报对伊朗导弹发射系统和防空系统实施打击",
        "url": "https://sputniknews.cn/20260301/1069987870.html"
      },
      {
        "title": "特朗普称伊朗最高领袖已死亡",
        "url": "https://sputniknews.cn/20260301/1069987764.html"
      },
      {
        "title": "美国放弃让伊朗前国王之子出任伊朗领导人的计划",
        "url": "https://sputniknews.cn/20260301/1069987600.html"
      },
      {
        "title": "媒体：伊朗方面证实最高领袖阿里·哈梅内伊的四名家属身亡",
        "url": "https://sputniknews.cn/20260301/1069987487.html"
      },
      {
        "title": "特朗普：因伊朗不愿达成协议而发动袭击",
        "url": "https://sputniknews.cn/20260301/1069987370.html"
      },
      {
        "title": "美国空军加油机从美国飞往中东",
        "url": "https://sputniknews.cn/20260301/1069987239.html"
      },
      {
        "title": "联合国安理会就有关伊朗的局势召开紧急会议",
        "url": "https://sputniknews.cn/20260301/1069987103.html"
      }
    ]
  },
  {
    "id": "cankaoxiaoxi",
    "items": [
      {
        "title": "法媒：德黑兰响起新一轮爆炸声",
        "url": "https://ckxxapp.ckxx.net/pages/2026/03/01/26543526fa4042478aedf2363f15e172.html"
      },
      {
        "title": "以军出动约200架战斗机，声称是以空军史上最大规模越境军事行动",
        "url": "https://ckxxapp.ckxx.net/pages/2026/03/01/45f16fb9dec34965829cf1c5b331fd04.html"
      },
      {
        "title": "伊朗革命卫队：将开始对美以展开“史上最猛烈进攻”",
        "url": "https://ckxxapp.ckxx.net/pages/2026/03/01/bacd129a80b54c738c8df524a1c2ec45.html"
      },
      {
        "title": "俄媒：伊朗总统府表示哈梅内伊之死不会没有回应",
        "url": "https://ckxxapp.ckxx.net/pages/2026/03/01/3e979ecce35e43cc84c72c36607d1fd0.html"
      },
      {
        "title": "伊朗红新月会：美以袭击致至少201人死747人伤",
        "url": "https://ckxxapp.ckxx.net/pages/2026/03/01/a5400d034c594f608213564c3be9fe6f.html"
      },
      {
        "title": "白宫发布特朗普“观战”照片",
        "url": "https://ckxxapp.ckxx.net/pages/2026/03/01/d21059453f24428696b5c39f835d0281.html"
      },
      {
        "title": "伊朗伊斯兰革命卫队：霍尔木兹海峡对船只关闭",
        "url": "https://ckxxapp.ckxx.net/pages/2026/03/01/c75f53f0f87e439b9a9e71cd3aafa49c.html"
      },
      {
        "title": "德媒：默茨下周再度访美，这次可能“更具对抗性”",
        "url": "https://ckxxapp.ckxx.net/pages/2026/02/28/5e67d598cf24486884a525ad495ea519.html"
      },
      {
        "title": "德媒分析：伊朗导弹库能在短期内与美军抗衡",
        "url": "https://ckxxapp.ckxx.net/pages/2026/02/28/2b1bb8f3707042eabc16786c96dae38f.html"
      },
      {
        "title": "伊朗政府声明：战时储备充足",
        "url": "https://ckxxapp.ckxx.net/pages/2026/02/28/b73b8bb4680e485d876667629d320587.html"
      },
      {
        "title": "伊朗伊斯兰革命卫队指挥官：伊朗目前使用的只是“废旧导弹”",
        "url": "https://ckxxapp.ckxx.net/pages/2026/02/28/39bc1eb857ef477c90764639c33b49e6.html"
      },
      {
        "title": "法媒：约旦宣布击落两枚弹道导弹",
        "url": "https://ckxxapp.ckxx.net/pages/2026/02/28/873eb30016b041ada051a24add8323e2.html"
      },
      {
        "title": "美伊调解人发声：敦促美国收手",
        "url": "https://ckxxapp.ckxx.net/pages/2026/02/28/7272428da8d24b43a0c6ffabe36ece68.html"
      },
      {
        "title": "美以对伊朗动手，俄罗斯、欧盟、巴基斯坦等多方发声",
        "url": "https://ckxxapp.ckxx.net/pages/2026/02/28/44983a969aad4dcaa0ae371e23137dec.html"
      },
      {
        "title": "外媒：德黑兰宣布公共交通免费助市民逃难",
        "url": "https://ckxxapp.ckxx.net/pages/2026/02/28/7c054cc7f80c48589c45459dc3b9e354.html"
      },
      {
        "title": "外交部发言人就美国和以色列军事打击伊朗答记者问",
        "url": "https://ckxxapp.ckxx.net/pages/2026/02/28/e23c698c7b974c9780a143a041d5b9f8.html"
      },
      {
        "title": "美媒：哈梅内伊和内贾德住所遭袭",
        "url": "https://ckxxapp.ckxx.net/pages/2026/02/28/52471cd4e60e4d798e1d7ba9d275c420.html"
      },
      {
        "title": "外媒：监控对伊行动，特朗普等人行踪曝光",
        "url": "https://ckxxapp.ckxx.net/pages/2026/02/28/fafc4a6ef6b145b2856198e331fcf840.html"
      },
      {
        "title": "梅德韦杰夫：美伊谈判是掩人耳目之举，没人想与伊朗达成协议",
        "url": "https://ckxxapp.ckxx.net/pages/2026/02/28/439c760d65104f0082407059467a0ec4.html"
      },
      {
        "title": "外媒：阿联酋、科威特称已对来袭导弹作出回应",
        "url": "https://ckxxapp.ckxx.net/pages/2026/02/28/6b151ca946eb4f75bc9d2abdf7292352.html"
      },
      {
        "title": "外媒：阿联酋、伊拉克、伊朗均有人在冲突中丧生",
        "url": "https://ckxxapp.ckxx.net/pages/2026/02/28/e1e918047314409fabc2d9f04ffc1bed.html"
      },
      {
        "title": "外媒：伊朗向以色列发射新一波导弹",
        "url": "https://ckxxapp.ckxx.net/pages/2026/02/28/e0f6f17203ba45a7a59d04982ab498bc.html"
      },
      {
        "title": "以军方：美以联合空袭已打击伊朗境内“数十个军事目标”",
        "url": "https://ckxxapp.ckxx.net/pages/2026/02/28/5afe1f210d7b4c969fa065d65327449e.html"
      },
      {
        "title": "外媒：耶路撒冷上空响起爆炸声",
        "url": "https://ckxxapp.ckxx.net/pages/2026/02/28/3d7e074a57ac4162a1168b180338a367.html"
      },
      {
        "title": "美媒：美海军第五舰队巴林驻地遇袭",
        "url": "https://ckxxapp.ckxx.net/pages/2026/02/28/49514c29e38f4ef9b694d456aae570df.html"
      },
      {
        "title": "外媒：伊朗军队总司令哈塔米“安然无恙”",
        "url": "https://ckxxapp.ckxx.net/pages/2026/02/28/abe1ba2ebb764cebb54546a384d44406.html"
      },
      {
        "title": "伊朗：袭击了驻卡塔尔、科威特、阿联酋和巴林的美军目标",
        "url": "https://ckxxapp.ckxx.net/pages/2026/02/28/048f39296cf6404dbf360a0edd7b1c3b.html"
      },
      {
        "title": "韩国投资者青睐中国科技股",
        "url": "https://ckxxapp.ckxx.net/pages/2026/02/28/836bf9a4bd0b4a71aec2af7315e663b1.html"
      },
      {
        "title": "港媒：“运动度假”在中国年轻人中风靡",
        "url": "https://ckxxapp.ckxx.net/pages/2026/02/28/1c5c987debc04603a2d0200c6d626df8.html"
      },
      {
        "title": "“8D城市”重庆令港媒记者惊叹沉醉",
        "url": "https://ckxxapp.ckxx.net/pages/2026/02/28/9f25b67e961f4390b5ea9c0f694aa57b.html"
      }
    ]
  },
  {
    "id": "kaopu",
    "items": [
      {
        "title": "「梦境工程」让我们更快乐 —— 还能让我们买更多啤酒？",
        "url": "https://www.bbc.com/zhongwen/articles/cn0z9g50rpvo/simp"
      },
      {
        "title": "分析：这是一个危险时刻，但美国与以色列认为机不可失",
        "url": "https://www.bbc.com/zhongwen/articles/c5yg953jd4wo/simp"
      },
      {
        "title": "关于美国袭击伊朗，你应该了解的最新信息",
        "url": "https://cn.nytimes.com/usa/20260301/iran-attacks-what-to-know/"
      },
      {
        "title": "特朗普为何选择此时对伊朗发动攻击",
        "url": "https://cn.nytimes.com/usa/20260301/trump-iran-attack/"
      }
    ]
  }
]